{
	"configurations" : 
	[
		{
			"directories" : 
			[
				{
					"build" : ".",
					"jsonFile" : "directory-.-Debug-d0094a50bb2071803777.json",
					"minimumCMakeVersion" : 
					{
						"string" : "3.30"
					},
					"projectIndex" : 0,
					"source" : ".",
					"targetIndexes" : 
					[
						0
					]
				}
			],
			"name" : "Debug",
			"projects" : 
			[
				{
					"directoryIndexes" : 
					[
						0
					],
					"name" : "insert_or_assign",
					"targetIndexes" : 
					[
						0
					]
				}
			],
			"targets" : 
			[
				{
					"directoryIndex" : 0,
					"id" : "insert_or_assign::@6890427a1f51a3e7e1df",
					"jsonFile" : "target-insert_or_assign-Debug-5c5fa73ce026faf1cc66.json",
					"name" : "insert_or_assign",
					"projectIndex" : 0
				}
			]
		}
	],
	"kind" : "codemodel",
	"paths" : 
	{
		"build" : "G:/c++/STL/STL/map/insert_or_assign/cmake-build-debug",
		"source" : "G:/c++/STL/STL/map/insert_or_assign"
	},
	"version" : 
	{
		"major" : 2,
		"minor" : 7
	}
}
